academlo/__init__.py
academlo/api.py
academlo/middleware.py
academlo/response.py
academlo-0.0.5.dist-info/WHEEL
academlo-0.0.5.dist-info/METADATA
academlo-0.0.5.dist-info/RECORD
