Metadata-Version: 2.1
Name: academlo
Version: 0.0.5
Summary: 
Author: Nicolas
Author-email: nicolas.rondon@academlo.com
Requires-Python: >=3.8,<4.0
Classifier: Programming Language :: Python :: 3
Classifier: Programming Language :: Python :: 3.10
Classifier: Programming Language :: Python :: 3.8
Classifier: Programming Language :: Python :: 3.9
